doc2txt/__init__.py
doc2txt/antiword_wrapper.py
doc2txt/text_optimizer.py
doc2txt/antiword_share/8859-1.txt
doc2txt/antiword_share/8859-10.txt
doc2txt/antiword_share/8859-11.txt
doc2txt/antiword_share/8859-13.txt
doc2txt/antiword_share/8859-14.txt
doc2txt/antiword_share/8859-15.txt
doc2txt/antiword_share/8859-16.txt
doc2txt/antiword_share/8859-2.txt
doc2txt/antiword_share/8859-3.txt
doc2txt/antiword_share/8859-4.txt
doc2txt/antiword_share/8859-5.txt
doc2txt/antiword_share/8859-6.txt
doc2txt/antiword_share/8859-7.txt
doc2txt/antiword_share/8859-8.txt
doc2txt/antiword_share/8859-9.txt
doc2txt/antiword_share/MacCyrillic.txt
doc2txt/antiword_share/MacRoman.txt
doc2txt/antiword_share/UTF-8.txt
doc2txt/antiword_share/cp1250.txt
doc2txt/antiword_share/cp1251.txt
doc2txt/antiword_share/cp1252.txt
doc2txt/antiword_share/cp437.txt
doc2txt/antiword_share/cp850.txt
doc2txt/antiword_share/cp852.txt
doc2txt/antiword_share/cp862.txt
doc2txt/antiword_share/cp864.txt
doc2txt/antiword_share/cp866.txt
doc2txt/antiword_share/fontnames
doc2txt/antiword_share/koi8-r.txt
doc2txt/antiword_share/koi8-u.txt
doc2txt/antiword_share/roman.txt
doc2txt/bin/darwin-arm64/antiword
doc2txt/bin/linux-amd64/antiword
doc2txt/bin/win-amd64/antiword.exe
doc2txt-1.0.7.dist-info/licenses/LICENSE.md
doc2txt-1.0.7.dist-info/METADATA
doc2txt-1.0.7.dist-info/WHEEL
doc2txt-1.0.7.dist-info/top_level.txt
doc2txt-1.0.7.dist-info/RECORD
