Metadata-Version: 2.4
Name: doc2txt
Version: 1.0.7
Summary: Python wrapper for antiword with bundled binary and data files
Home-page: https://github.com/quantatirsk/doc2txt-pypi
Author: Quant
Author-email: pengzhia@mail.com
License: MIT
Project-URL: Bug Reports, https://github.com/quantatirsk/doc2txt-pypi/issues
Project-URL: Source, https://github.com/quantatirsk/doc2txt-pypi
Keywords: word doc text extraction antiword document
Classifier: Development Status :: 4 - Beta
Classifier: Intended Audience :: Developers
Classifier: License :: OSI Approved :: MIT License
Classifier: Programming Language :: Python :: 3
Classifier: Programming Language :: Python :: 3.6
Classifier: Programming Language :: Python :: 3.7
Classifier: Programming Language :: Python :: 3.8
Classifier: Programming Language :: Python :: 3.9
Classifier: Programming Language :: Python :: 3.10
Classifier: Programming Language :: Python :: 3.11
Classifier: Programming Language :: Python :: 3.12
Classifier: Operating System :: OS Independent
Classifier: Topic :: Text Processing
Classifier: Topic :: Office/Business :: Office Suites
Requires-Python: >=3.6
License-File: LICENSE.md
Requires-Dist: chardet>=5.2.0
Requires-Dist: fast-langdetect>=0.4.6
Dynamic: author
Dynamic: author-email
Dynamic: classifier
Dynamic: description
Dynamic: description-content-type
Dynamic: home-page
Dynamic: keywords
Dynamic: license
Dynamic: license-file
Dynamic: project-url
Dynamic: requires-dist
Dynamic: requires-python
Dynamic: summary
